claude_here/__coconut__.py
claude_here/__init__.py
claude_here/debugger.py
claude_here/launcher.py
claude_here/main.py
claude_here/prompter.py
claude_here/tests.py
claude_here/util.py
claude_here/test_files/fib_test.py
claude_here-0.2.3.dist-info/LICENSE
claude_here-0.2.3.dist-info/METADATA
claude_here-0.2.3.dist-info/WHEEL
claude_here-0.2.3.dist-info/top_level.txt
claude_here-0.2.3.dist-info/RECORD
