Metadata-Version: 2.1
Name: claude_here
Version: 0.2.3
Summary: debug Python with claude.ai
Author-email: Evan Hubinger <evanjhub@gmail.com>
Project-URL: Homepage, https://github.com/evhub/claude-here
Project-URL: Issues, https://github.com/evhub/claude-here/issues
Classifier: Programming Language :: Python :: 3
Classifier: License :: OSI Approved :: Apache Software License
Classifier: Operating System :: OS Independent
Requires-Python: >=3.9
License-File: LICENSE
